README.rst
setup.cfg
setup.py
mist/__init__.py
mist/__version__.py
mist/app.py
mist/cli.py
mist/models.py
mist_cli.egg-info/PKG-INFO
mist_cli.egg-info/SOURCES.txt
mist_cli.egg-info/dependency_links.txt
mist_cli.egg-info/entry_points.txt
mist_cli.egg-info/not-zip-safe
mist_cli.egg-info/requires.txt
mist_cli.egg-info/top_level.txt