Metadata-Version: 1.1
Name: mist-cli
Version: 1.0.4
Summary: Mist command line tool
Home-page: https://hydrosphere.io/mist
Author: Hydrospheredata
Author-email: info@hydrosphere.io
License: Apache 2.0
Platform: UNKNOWN
Classifier: Development Status :: 3 - Alpha
Classifier: Intended Audience :: Developers
Classifier: Natural Language :: English
Classifier: License :: OSI Approved :: Apache Software License
Classifier: Programming Language :: Python
Classifier: Programming Language :: Python :: 2.7
Classifier: Programming Language :: Python :: 3.4
Classifier: Programming Language :: Python :: 3.5
